{
  "facilityId": 1000077343,
  "epaFacId": "100000154281",
  "facNm": "Martin, TN",
  "parntCo1Nm": "Weakley Farmers Coop",
  "facDunsNu": 34737171,
  "sbmsnTypeCd": "R",
  "facStreet1Tx": "330 Nash Street",
  "facStreet2Tx": null,
  "facCityNm": "Martin",
  "facStateCd": "TN",
  "countyNm": "WEAKLEY",
  "facZipCd": "38237",
  "facZip4Cd": null,
  "receiptDa": "2019-06-04T10:48:13.000",
  "facLatDecMs": "36.342150",
  "facLongDecMs": "-088.840137",
  "lepcNm": "Weakley County LEPC",
  "oshaPsmCd": null,
  "epcra302Cd": "Y",
  "caaTitleVCd": null,
  "deregisteredDate": null,
  "emergencyPlan": {
    "communityPlanCd": "Y",
    "facilityPlanCd": null,
    "responseActionsCd": null,
    "publicProceduresCd": null,
    "healthcareCd": null,
    "agencyNm": "Fire Department",
    "agencyPhoneNm": "7315875139",
    "_links": {
      "facility": {
        "href": "https://cdxapps.epa.gov/olem-rmp-pds/api/facilities/1000077343"
      }
    }
  },
  "processes": [
    {
      "programLevelCd": 2,
      "processNaics": [
        {
          "description": "Farm Supplies Merchant Wholesalers ",
          "naicsCd": "42491",
          "_links": {
            "naics": {
              "href": "https://cdxapps.epa.gov/olem-rmp-pds/api/naics-codes/42491"
            }
          }
        }
      ],
      "processChemicals": [
        {
          "flammableMixChems": [],
          "chemicalNm": "Ammonia (anhydrous)",
          "casNu": "7664-41-7",
          "flamToxCd": "T",
          "_links": {
            "chemical": {
              "href": "https://cdxapps.epa.gov/olem-rmp-pds/api/chemicals/56"
            }
          }
        }
      ],
      "_links": {
        "facility": {
          "href": "https://cdxapps.epa.gov/olem-rmp-pds/api/facilities/1000077343"
        }
      }
    }
  ],
  "_links": {
    "self": {
      "href": "https://cdxapps.epa.gov/olem-rmp-pds/api/facilities/1000077343"
    },
    "facility": {
      "href": "https://cdxapps.epa.gov/olem-rmp-pds/api/facilities/1000077343"
    }
  }
}