{
  "facilityId": 1000104647,
  "epaFacId": "100000217883",
  "facNm": "Central Farm Service ",
  "parntCo1Nm": "",
  "facDunsNu": 80146911,
  "sbmsnTypeCd": "R",
  "facStreet1Tx": "201 Main Street West",
  "facStreet2Tx": "PO Box 127",
  "facCityNm": "Clarks Grove",
  "facStateCd": "MN",
  "countyNm": "FREEBORN",
  "facZipCd": "56016",
  "facZip4Cd": "",
  "receiptDa": "2023-03-22T00:00:00.000",
  "facLatDecMs": "43.760729",
  "facLongDecMs": "-93.332209",
  "lepcNm": "Regional Rev Comm Dist#1 ",
  "oshaPsmCd": null,
  "epcra302Cd": "Y",
  "caaTitleVCd": null,
  "deregisteredDate": null,
  "emergencyPlan": {
    "communityPlanCd": "Y",
    "facilityPlanCd": "Y",
    "responseActionsCd": "Y",
    "publicProceduresCd": "Y",
    "healthcareCd": "Y",
    "agencyNm": "Clarks Grove Fire Department ",
    "agencyPhoneNm": "5072564106",
    "_links": {
      "facility": {
        "href": "https://cdxapps.epa.gov/olem-rmp-pds/api/facilities/1000104647"
      }
    }
  },
  "processes": [
    {
      "programLevelCd": 2,
      "processNaics": [
        {
          "description": "Farm Supplies Merchant Wholesalers ",
          "naicsCd": "42491",
          "_links": {
            "naics": {
              "href": "https://cdxapps.epa.gov/olem-rmp-pds/api/naics-codes/42491"
            }
          }
        }
      ],
      "processChemicals": [
        {
          "flammableMixChems": [],
          "chemicalNm": "Ammonia (anhydrous)",
          "casNu": "7664-41-7",
          "flamToxCd": "T",
          "_links": {
            "chemical": {
              "href": "https://cdxapps.epa.gov/olem-rmp-pds/api/chemicals/56"
            }
          }
        }
      ],
      "_links": {
        "facility": {
          "href": "https://cdxapps.epa.gov/olem-rmp-pds/api/facilities/1000104647"
        }
      }
    }
  ],
  "_links": {
    "self": {
      "href": "https://cdxapps.epa.gov/olem-rmp-pds/api/facilities/1000104647"
    },
    "facility": {
      "href": "https://cdxapps.epa.gov/olem-rmp-pds/api/facilities/1000104647"
    }
  }
}