{
  "facilityId": 1000086744,
  "epaFacId": "100000211692",
  "facNm": "HWTG - Columbia",
  "parntCo1Nm": "",
  "facDunsNu": 5073659,
  "sbmsnTypeCd": "R",
  "facStreet1Tx": "1400 East Boone Industrial Drive",
  "facStreet2Tx": "",
  "facCityNm": "Columbia",
  "facStateCd": "MO",
  "countyNm": "BOONE",
  "facZipCd": "65202",
  "facZip4Cd": "",
  "receiptDa": "2020-04-21T00:00:00.000",
  "facLatDecMs": "38.997698",
  "facLongDecMs": "-92.319335",
  "lepcNm": "Boone County LEPC",
  "oshaPsmCd": "Y",
  "epcra302Cd": "Y",
  "caaTitleVCd": null,
  "deregisteredDate": null,
  "emergencyPlan": {
    "communityPlanCd": "Y",
    "facilityPlanCd": null,
    "responseActionsCd": null,
    "publicProceduresCd": null,
    "healthcareCd": null,
    "agencyNm": "Boone County Fire Department",
    "agencyPhoneNm": "5734413800",
    "_links": {
      "facility": {
        "href": "https://cdxapps.epa.gov/olem-rmp-pds/api/facilities/1000086744"
      }
    }
  },
  "processes": [
    {
      "programLevelCd": 3,
      "processNaics": [
        {
          "description": "Other Chemical and Allied Products Merchant Wholesalers ",
          "naicsCd": "42469",
          "_links": {
            "naics": {
              "href": "https://cdxapps.epa.gov/olem-rmp-pds/api/naics-codes/42469"
            }
          }
        }
      ],
      "processChemicals": [
        {
          "flammableMixChems": [],
          "chemicalNm": "Sulfur dioxide (anhydrous)",
          "casNu": "7446-09-5",
          "flamToxCd": "T",
          "_links": {
            "chemical": {
              "href": "https://cdxapps.epa.gov/olem-rmp-pds/api/chemicals/49"
            }
          }
        },
        {
          "flammableMixChems": [],
          "chemicalNm": "Chlorine",
          "casNu": "7782-50-5",
          "flamToxCd": "T",
          "_links": {
            "chemical": {
              "href": "https://cdxapps.epa.gov/olem-rmp-pds/api/chemicals/62"
            }
          }
        }
      ],
      "_links": {
        "facility": {
          "href": "https://cdxapps.epa.gov/olem-rmp-pds/api/facilities/1000086744"
        }
      }
    }
  ],
  "_links": {
    "self": {
      "href": "https://cdxapps.epa.gov/olem-rmp-pds/api/facilities/1000086744"
    },
    "facility": {
      "href": "https://cdxapps.epa.gov/olem-rmp-pds/api/facilities/1000086744"
    }
  }
}