{
  "facilityId": 1000000227,
  "epaFacId": "100000085551",
  "facNm": "Highwood",
  "parntCo1Nm": "Mountain View Co-op",
  "facDunsNu": null,
  "sbmsnTypeCd": "R",
  "facStreet1Tx": "Highway 87 E 5 miles, East on 228",
  "facStreet2Tx": "towards Highwood 8.4 miles",
  "facCityNm": "Great Falls",
  "facStateCd": "MT",
  "countyNm": "CASCADE",
  "facZipCd": "59405",
  "facZip4Cd": null,
  "receiptDa": "2009-06-09T00:00:00.000",
  "facLatDecMs": "47.498056",
  "facLongDecMs": "-111.000250",
  "lepcNm": "Cascade LEPC",
  "oshaPsmCd": null,
  "epcra302Cd": "Y",
  "caaTitleVCd": null,
  "deregisteredDate": "2013-11-15T00:00:00.000",
  "emergencyPlan": {
    "communityPlanCd": "Y",
    "facilityPlanCd": "Y",
    "responseActionsCd": "Y",
    "publicProceduresCd": "Y",
    "healthcareCd": "Y",
    "agencyNm": "Local Emergency Planning Committee",
    "agencyPhoneNm": "4065456900",
    "_links": {
      "facility": {
        "href": "https://cdxapps.epa.gov/olem-rmp-pds/api/facilities/1000000227"
      }
    }
  },
  "processes": [
    {
      "programLevelCd": 2,
      "processNaics": [
        {
          "description": "All Other Crop Farming",
          "naicsCd": "11199",
          "_links": {
            "naics": {
              "href": "https://cdxapps.epa.gov/olem-rmp-pds/api/naics-codes/11199"
            }
          }
        }
      ],
      "processChemicals": [
        {
          "flammableMixChems": [],
          "chemicalNm": "Ammonia (anhydrous)",
          "casNu": "7664-41-7",
          "flamToxCd": "T",
          "_links": {
            "chemical": {
              "href": "https://cdxapps.epa.gov/olem-rmp-pds/api/chemicals/56"
            }
          }
        }
      ],
      "_links": {
        "facility": {
          "href": "https://cdxapps.epa.gov/olem-rmp-pds/api/facilities/1000000227"
        }
      }
    }
  ],
  "_links": {
    "self": {
      "href": "https://cdxapps.epa.gov/olem-rmp-pds/api/facilities/1000000227"
    },
    "facility": {
      "href": "https://cdxapps.epa.gov/olem-rmp-pds/api/facilities/1000000227"
    }
  }
}