{
  "facilityId": 21538,
  "epaFacId": "100000170717",
  "facNm": "Pittsburg Water Treatment Plant",
  "parntCo1Nm": "City of Pittsburg, California",
  "facDunsNu": null,
  "sbmsnTypeCd": "F",
  "facStreet1Tx": "300 Olympic Drive",
  "facStreet2Tx": null,
  "facCityNm": "Pittsburg",
  "facStateCd": "CA",
  "countyNm": "CONTRA COSTA",
  "facZipCd": "94565",
  "facZip4Cd": null,
  "receiptDa": "2000-06-21T00:00:00.000",
  "facLatDecMs": "38.008333",
  "facLongDecMs": "-121.902778",
  "lepcNm": "Region II LEPC",
  "oshaPsmCd": null,
  "epcra302Cd": "Y",
  "caaTitleVCd": null,
  "deregisteredDate": null,
  "emergencyPlan": {
    "communityPlanCd": "Y",
    "facilityPlanCd": "Y",
    "responseActionsCd": "Y",
    "publicProceduresCd": "Y",
    "healthcareCd": "Y",
    "agencyNm": "Contra Costa County Environ. Health",
    "agencyPhoneNm": "9256462286",
    "_links": {
      "facility": {
        "href": "https://cdxapps.epa.gov/olem-rmp-pds/api/facilities/21538"
      }
    }
  },
  "processes": [
    {
      "programLevelCd": 2,
      "processNaics": [
        {
          "description": "Water Supply and Irrigation Systems ",
          "naicsCd": "22131",
          "_links": {
            "naics": {
              "href": "https://cdxapps.epa.gov/olem-rmp-pds/api/naics-codes/22131"
            }
          }
        }
      ],
      "processChemicals": [
        {
          "flammableMixChems": [],
          "chemicalNm": "Chlorine",
          "casNu": "7782-50-5",
          "flamToxCd": "T",
          "_links": {
            "chemical": {
              "href": "https://cdxapps.epa.gov/olem-rmp-pds/api/chemicals/62"
            }
          }
        }
      ],
      "_links": {
        "facility": {
          "href": "https://cdxapps.epa.gov/olem-rmp-pds/api/facilities/21538"
        }
      }
    },
    {
      "programLevelCd": 2,
      "processNaics": [
        {
          "description": "Water Supply and Irrigation Systems ",
          "naicsCd": "22131",
          "_links": {
            "naics": {
              "href": "https://cdxapps.epa.gov/olem-rmp-pds/api/naics-codes/22131"
            }
          }
        }
      ],
      "processChemicals": [
        {
          "flammableMixChems": [],
          "chemicalNm": "Ammonia (anhydrous)",
          "casNu": "7664-41-7",
          "flamToxCd": "T",
          "_links": {
            "chemical": {
              "href": "https://cdxapps.epa.gov/olem-rmp-pds/api/chemicals/56"
            }
          }
        }
      ],
      "_links": {
        "facility": {
          "href": "https://cdxapps.epa.gov/olem-rmp-pds/api/facilities/21538"
        }
      }
    }
  ],
  "_links": {
    "self": {
      "href": "https://cdxapps.epa.gov/olem-rmp-pds/api/facilities/21538"
    },
    "facility": {
      "href": "https://cdxapps.epa.gov/olem-rmp-pds/api/facilities/21538"
    }
  }
}