{
  "facilityId": 14491,
  "epaFacId": "100000017714",
  "facNm": "Poseyville Branch",
  "parntCo1Nm": "POSEY COUNTY FARM BUREAU COOP",
  "facDunsNu": null,
  "sbmsnTypeCd": "R",
  "facStreet1Tx": "151 SOUTH LOCKWOOD",
  "facStreet2Tx": null,
  "facCityNm": "POSEYVILLE",
  "facStateCd": "IN",
  "countyNm": "POSEY",
  "facZipCd": "47633",
  "facZip4Cd": null,
  "receiptDa": "1999-07-01T00:00:00.000",
  "facLatDecMs": "38.166111",
  "facLongDecMs": "-87.785556",
  "lepcNm": "posey County LEPC",
  "oshaPsmCd": null,
  "epcra302Cd": "Y",
  "caaTitleVCd": null,
  "deregisteredDate": null,
  "emergencyPlan": {
    "communityPlanCd": "Y",
    "facilityPlanCd": "Y",
    "responseActionsCd": "Y",
    "publicProceduresCd": "Y",
    "healthcareCd": "Y",
    "agencyNm": "LEPC",
    "agencyPhoneNm": "8128381320",
    "_links": {
      "facility": {
        "href": "https://cdxapps.epa.gov/olem-rmp-pds/api/facilities/14491"
      }
    }
  },
  "processes": [
    {
      "programLevelCd": 2,
      "processNaics": [
        {
          "description": "Farm Supplies Wholesalers",
          "naicsCd": "42291",
          "_links": {
            "naics": {
              "href": "https://cdxapps.epa.gov/olem-rmp-pds/api/naics-codes/42291"
            }
          }
        }
      ],
      "processChemicals": [
        {
          "flammableMixChems": [],
          "chemicalNm": "Ammonia (anhydrous)",
          "casNu": "7664-41-7",
          "flamToxCd": "T",
          "_links": {
            "chemical": {
              "href": "https://cdxapps.epa.gov/olem-rmp-pds/api/chemicals/56"
            }
          }
        }
      ],
      "_links": {
        "facility": {
          "href": "https://cdxapps.epa.gov/olem-rmp-pds/api/facilities/14491"
        }
      }
    }
  ],
  "_links": {
    "self": {
      "href": "https://cdxapps.epa.gov/olem-rmp-pds/api/facilities/14491"
    },
    "facility": {
      "href": "https://cdxapps.epa.gov/olem-rmp-pds/api/facilities/14491"
    }
  }
}