{
  "facilityId": 4514,
  "epaFacId": "100000055806",
  "facNm": "First Utility District of Knox County WWTP",
  "parntCo1Nm": null,
  "facDunsNu": null,
  "sbmsnTypeCd": "F",
  "facStreet1Tx": "1051 Concord Road",
  "facStreet2Tx": null,
  "facCityNm": "Knoxville",
  "facStateCd": "TN",
  "countyNm": "KNOX",
  "facZipCd": "37922",
  "facZip4Cd": null,
  "receiptDa": "1999-06-18T00:00:00.000",
  "facLatDecMs": "35.861861",
  "facLongDecMs": "-84.14725",
  "lepcNm": null,
  "oshaPsmCd": "Y",
  "epcra302Cd": "Y",
  "caaTitleVCd": null,
  "deregisteredDate": "2009-04-24T00:00:00.000",
  "emergencyPlan": {
    "communityPlanCd": "Y",
    "facilityPlanCd": "Y",
    "responseActionsCd": "Y",
    "publicProceduresCd": "Y",
    "healthcareCd": "Y",
    "agencyNm": "Rural Metro Fire Department",
    "agencyPhoneNm": "4235885371",
    "_links": {
      "facility": {
        "href": "https://cdxapps.epa.gov/olem-rmp-pds/api/facilities/4514"
      }
    }
  },
  "processes": [
    {
      "programLevelCd": 3,
      "processNaics": [
        {
          "description": "Sewage Treatment Facilities ",
          "naicsCd": "22132",
          "_links": {
            "naics": {
              "href": "https://cdxapps.epa.gov/olem-rmp-pds/api/naics-codes/22132"
            }
          }
        }
      ],
      "processChemicals": [
        {
          "flammableMixChems": [],
          "chemicalNm": "Chlorine",
          "casNu": "7782-50-5",
          "flamToxCd": "T",
          "_links": {
            "chemical": {
              "href": "https://cdxapps.epa.gov/olem-rmp-pds/api/chemicals/62"
            }
          }
        }
      ],
      "_links": {
        "facility": {
          "href": "https://cdxapps.epa.gov/olem-rmp-pds/api/facilities/4514"
        }
      }
    }
  ],
  "_links": {
    "self": {
      "href": "https://cdxapps.epa.gov/olem-rmp-pds/api/facilities/4514"
    },
    "facility": {
      "href": "https://cdxapps.epa.gov/olem-rmp-pds/api/facilities/4514"
    }
  }
}