{
  "_embedded": [
    {
      "facilityId": 1000112798,
      "epaFacId": "100000090849",
      "facNm": null,
      "parntCo1Nm": null,
      "facDunsNu": null,
      "sbmsnTypeCd": "R",
      "facStreet1Tx": null,
      "facStreet2Tx": null,
      "facCityNm": null,
      "facStateCd": null,
      "countyNm": null,
      "facZipCd": null,
      "facZip4Cd": null,
      "receiptDa": "2024-06-27T00:00:00.000",
      "facLatDecMs": null,
      "facLongDecMs": null,
      "lepcNm": null,
      "oshaPsmCd": null,
      "epcra302Cd": null,
      "caaTitleVCd": null,
      "deregisteredDate": null,
      "emergencyPlan": null,
      "processes": null
    },
    {
      "facilityId": 1000107523,
      "epaFacId": "100000090849",
      "facNm": null,
      "parntCo1Nm": null,
      "facDunsNu": null,
      "sbmsnTypeCd": "R",
      "facStreet1Tx": null,
      "facStreet2Tx": null,
      "facCityNm": null,
      "facStateCd": null,
      "countyNm": null,
      "facZipCd": null,
      "facZip4Cd": null,
      "receiptDa": "2023-10-31T00:00:00.000",
      "facLatDecMs": null,
      "facLongDecMs": null,
      "lepcNm": null,
      "oshaPsmCd": null,
      "epcra302Cd": null,
      "caaTitleVCd": null,
      "deregisteredDate": null,
      "emergencyPlan": null,
      "processes": null
    },
    {
      "facilityId": 1000073720,
      "epaFacId": "100000090849",
      "facNm": null,
      "parntCo1Nm": null,
      "facDunsNu": null,
      "sbmsnTypeCd": "R",
      "facStreet1Tx": null,
      "facStreet2Tx": null,
      "facCityNm": null,
      "facStateCd": null,
      "countyNm": null,
      "facZipCd": null,
      "facZip4Cd": null,
      "receiptDa": "2018-11-01T00:00:00.000",
      "facLatDecMs": null,
      "facLongDecMs": null,
      "lepcNm": null,
      "oshaPsmCd": null,
      "epcra302Cd": null,
      "caaTitleVCd": null,
      "deregisteredDate": null,
      "emergencyPlan": null,
      "processes": null
    },
    {
      "facilityId": 1000037076,
      "epaFacId": "100000090849",
      "facNm": null,
      "parntCo1Nm": null,
      "facDunsNu": null,
      "sbmsnTypeCd": "R",
      "facStreet1Tx": null,
      "facStreet2Tx": null,
      "facCityNm": null,
      "facStateCd": null,
      "countyNm": null,
      "facZipCd": null,
      "facZip4Cd": null,
      "receiptDa": "2013-10-28T00:00:00.000",
      "facLatDecMs": null,
      "facLongDecMs": null,
      "lepcNm": null,
      "oshaPsmCd": null,
      "epcra302Cd": null,
      "caaTitleVCd": null,
      "deregisteredDate": null,
      "emergencyPlan": null,
      "processes": null
    },
    {
      "facilityId": 52851,
      "epaFacId": "100000090849",
      "facNm": null,
      "parntCo1Nm": null,
      "facDunsNu": null,
      "sbmsnTypeCd": "R",
      "facStreet1Tx": null,
      "facStreet2Tx": null,
      "facCityNm": null,
      "facStateCd": null,
      "countyNm": null,
      "facZipCd": null,
      "facZip4Cd": null,
      "receiptDa": "2008-10-29T00:00:00.000",
      "facLatDecMs": null,
      "facLongDecMs": null,
      "lepcNm": null,
      "oshaPsmCd": null,
      "epcra302Cd": null,
      "caaTitleVCd": null,
      "deregisteredDate": null,
      "emergencyPlan": null,
      "processes": null
    },
    {
      "facilityId": 50881,
      "epaFacId": "100000090849",
      "facNm": null,
      "parntCo1Nm": null,
      "facDunsNu": null,
      "sbmsnTypeCd": "R",
      "facStreet1Tx": null,
      "facStreet2Tx": null,
      "facCityNm": null,
      "facStateCd": null,
      "countyNm": null,
      "facZipCd": null,
      "facZip4Cd": null,
      "receiptDa": "2008-02-12T00:00:00.000",
      "facLatDecMs": null,
      "facLongDecMs": null,
      "lepcNm": null,
      "oshaPsmCd": null,
      "epcra302Cd": null,
      "caaTitleVCd": null,
      "deregisteredDate": null,
      "emergencyPlan": null,
      "processes": null
    },
    {
      "facilityId": 27618,
      "epaFacId": "100000090849",
      "facNm": null,
      "parntCo1Nm": null,
      "facDunsNu": null,
      "sbmsnTypeCd": "R",
      "facStreet1Tx": null,
      "facStreet2Tx": null,
      "facCityNm": null,
      "facStateCd": null,
      "countyNm": null,
      "facZipCd": null,
      "facZip4Cd": null,
      "receiptDa": "2003-02-27T00:00:00.000",
      "facLatDecMs": null,
      "facLongDecMs": null,
      "lepcNm": null,
      "oshaPsmCd": null,
      "epcra302Cd": null,
      "caaTitleVCd": null,
      "deregisteredDate": null,
      "emergencyPlan": null,
      "processes": null
    },
    {
      "facilityId": 6854,
      "epaFacId": "100000090849",
      "facNm": null,
      "parntCo1Nm": null,
      "facDunsNu": null,
      "sbmsnTypeCd": "F",
      "facStreet1Tx": null,
      "facStreet2Tx": null,
      "facCityNm": null,
      "facStateCd": null,
      "countyNm": null,
      "facZipCd": null,
      "facZip4Cd": null,
      "receiptDa": "1999-06-21T00:00:00.000",
      "facLatDecMs": null,
      "facLongDecMs": null,
      "lepcNm": null,
      "oshaPsmCd": null,
      "epcra302Cd": null,
      "caaTitleVCd": null,
      "deregisteredDate": null,
      "emergencyPlan": null,
      "processes": null
    }
  ]
}