{
  "facilityId": 1000061887,
  "epaFacId": "100000234114",
  "facNm": "Blount Fine Foods",
  "parntCo1Nm": null,
  "facDunsNu": null,
  "sbmsnTypeCd": "F",
  "facStreet1Tx": "2200 Redbud Blvd.",
  "facStreet2Tx": null,
  "facCityNm": "McKinney",
  "facStateCd": "TX",
  "countyNm": "COLLIN",
  "facZipCd": "75069",
  "facZip4Cd": null,
  "receiptDa": "2017-02-21T00:00:00.000",
  "facLatDecMs": "33.227809",
  "facLongDecMs": "-96.627972",
  "lepcNm": "Collin County LEPC",
  "oshaPsmCd": "Y",
  "epcra302Cd": "Y",
  "caaTitleVCd": null,
  "deregisteredDate": null,
  "emergencyPlan": {
    "communityPlanCd": null,
    "facilityPlanCd": "Y",
    "responseActionsCd": "Y",
    "publicProceduresCd": "Y",
    "healthcareCd": "Y",
    "agencyNm": "McKinney Fire Department",
    "agencyPhoneNm": "9725472850",
    "_links": {
      "facility": {
        "href": "https://cdxapps.epa.gov/olem-rmp-pds/api/facilities/1000061887"
      }
    }
  },
  "processes": [
    {
      "programLevelCd": 3,
      "processNaics": [
        {
          "description": "Frozen Specialty Food Manufacturing ",
          "naicsCd": "311412",
          "_links": {
            "naics": {
              "href": "https://cdxapps.epa.gov/olem-rmp-pds/api/naics-codes/311412"
            }
          }
        }
      ],
      "processChemicals": [
        {
          "flammableMixChems": [],
          "chemicalNm": "Ammonia (anhydrous)",
          "casNu": "7664-41-7",
          "flamToxCd": "T",
          "_links": {
            "chemical": {
              "href": "https://cdxapps.epa.gov/olem-rmp-pds/api/chemicals/56"
            }
          }
        }
      ],
      "_links": {
        "facility": {
          "href": "https://cdxapps.epa.gov/olem-rmp-pds/api/facilities/1000061887"
        }
      }
    }
  ],
  "_links": {
    "self": {
      "href": "https://cdxapps.epa.gov/olem-rmp-pds/api/facilities/1000061887"
    },
    "facility": {
      "href": "https://cdxapps.epa.gov/olem-rmp-pds/api/facilities/1000061887"
    }
  }
}