{
  "facilityId": 1000113355,
  "epaFacId": "100000098994",
  "facNm": "Sun Ag, Inc. - Cullom",
  "parntCo1Nm": "Sun Ag, Inc.",
  "facDunsNu": null,
  "sbmsnTypeCd": "R",
  "facStreet1Tx": "PO Box 276",
  "facStreet2Tx": "236 South Cherry",
  "facCityNm": "Cullom",
  "facStateCd": "IL",
  "countyNm": "LIVINGSTON",
  "facZipCd": "60929",
  "facZip4Cd": "",
  "receiptDa": "2024-06-21T00:00:00.000",
  "facLatDecMs": "40.875528",
  "facLongDecMs": "-088.262500",
  "lepcNm": "Livingston County LEPC",
  "oshaPsmCd": "Y",
  "epcra302Cd": "Y",
  "caaTitleVCd": null,
  "deregisteredDate": null,
  "emergencyPlan": {
    "communityPlanCd": "Y",
    "facilityPlanCd": "Y",
    "responseActionsCd": "Y",
    "publicProceduresCd": "Y",
    "healthcareCd": "Y",
    "agencyNm": "Fire Department",
    "agencyPhoneNm": "8156892241",
    "_links": {
      "facility": {
        "href": "https://cdxapps.epa.gov/olem-rmp-pds/api/facilities/1000113355"
      }
    }
  },
  "processes": [
    {
      "programLevelCd": 2,
      "processNaics": [
        {
          "description": "Farm Supplies Merchant Wholesalers ",
          "naicsCd": "42491",
          "_links": {
            "naics": {
              "href": "https://cdxapps.epa.gov/olem-rmp-pds/api/naics-codes/42491"
            }
          }
        }
      ],
      "processChemicals": [
        {
          "flammableMixChems": [],
          "chemicalNm": "Ammonia (anhydrous)",
          "casNu": "7664-41-7",
          "flamToxCd": "T",
          "_links": {
            "chemical": {
              "href": "https://cdxapps.epa.gov/olem-rmp-pds/api/chemicals/56"
            }
          }
        }
      ],
      "_links": {
        "facility": {
          "href": "https://cdxapps.epa.gov/olem-rmp-pds/api/facilities/1000113355"
        }
      }
    }
  ],
  "_links": {
    "self": {
      "href": "https://cdxapps.epa.gov/olem-rmp-pds/api/facilities/1000113355"
    },
    "facility": {
      "href": "https://cdxapps.epa.gov/olem-rmp-pds/api/facilities/1000113355"
    }
  }
}