{
  "facilityId": 9535,
  "epaFacId": "100000118204",
  "facNm": "15th Street Water Treatment Plant",
  "parntCo1Nm": "Town of Ocean City Public Works Division",
  "facDunsNu": null,
  "sbmsnTypeCd": "F",
  "facStreet1Tx": "1400 St. Louis Ave",
  "facStreet2Tx": null,
  "facCityNm": "Ocean City",
  "facStateCd": "MD",
  "countyNm": "WORCESTER",
  "facZipCd": "21842",
  "facZip4Cd": null,
  "receiptDa": "1999-06-22T00:00:00.000",
  "facLatDecMs": "38.39075",
  "facLongDecMs": "-74.095472",
  "lepcNm": "Ocean City LEPC",
  "oshaPsmCd": "Y",
  "epcra302Cd": "Y",
  "caaTitleVCd": null,
  "deregisteredDate": null,
  "emergencyPlan": {
    "communityPlanCd": "Y",
    "facilityPlanCd": "Y",
    "responseActionsCd": "Y",
    "publicProceduresCd": "Y",
    "healthcareCd": "Y",
    "agencyNm": "Ocean City Volunteer Fire Company",
    "agencyPhoneNm": "4102894346",
    "_links": {
      "facility": {
        "href": "https://cdxapps.epa.gov/olem-rmp-pds/api/facilities/9535"
      }
    }
  },
  "processes": [
    {
      "programLevelCd": 3,
      "processNaics": [
        {
          "description": "Water Supply and Irrigation Systems ",
          "naicsCd": "22131",
          "_links": {
            "naics": {
              "href": "https://cdxapps.epa.gov/olem-rmp-pds/api/naics-codes/22131"
            }
          }
        }
      ],
      "processChemicals": [
        {
          "flammableMixChems": [],
          "chemicalNm": "Chlorine",
          "casNu": "7782-50-5",
          "flamToxCd": "T",
          "_links": {
            "chemical": {
              "href": "https://cdxapps.epa.gov/olem-rmp-pds/api/chemicals/62"
            }
          }
        }
      ],
      "_links": {
        "facility": {
          "href": "https://cdxapps.epa.gov/olem-rmp-pds/api/facilities/9535"
        }
      }
    }
  ],
  "_links": {
    "self": {
      "href": "https://cdxapps.epa.gov/olem-rmp-pds/api/facilities/9535"
    },
    "facility": {
      "href": "https://cdxapps.epa.gov/olem-rmp-pds/api/facilities/9535"
    }
  }
}