{
  "_embedded": [
    {
      "facilityId": 1000092528,
      "epaFacId": "100000175124",
      "facNm": null,
      "parntCo1Nm": null,
      "facDunsNu": null,
      "sbmsnTypeCd": "R",
      "facStreet1Tx": null,
      "facStreet2Tx": null,
      "facCityNm": null,
      "facStateCd": null,
      "countyNm": null,
      "facZipCd": null,
      "facZip4Cd": null,
      "receiptDa": "2021-02-23T09:06:02.000",
      "facLatDecMs": null,
      "facLongDecMs": null,
      "lepcNm": null,
      "oshaPsmCd": null,
      "epcra302Cd": null,
      "caaTitleVCd": null,
      "deregisteredDate": null,
      "emergencyPlan": null,
      "processes": null
    },
    {
      "facilityId": 1000055697,
      "epaFacId": "100000175124",
      "facNm": null,
      "parntCo1Nm": null,
      "facDunsNu": null,
      "sbmsnTypeCd": "R",
      "facStreet1Tx": null,
      "facStreet2Tx": null,
      "facCityNm": null,
      "facStateCd": null,
      "countyNm": null,
      "facZipCd": null,
      "facZip4Cd": null,
      "receiptDa": "2016-02-22T00:00:00.000",
      "facLatDecMs": null,
      "facLongDecMs": null,
      "lepcNm": null,
      "oshaPsmCd": null,
      "epcra302Cd": null,
      "caaTitleVCd": null,
      "deregisteredDate": null,
      "emergencyPlan": null,
      "processes": null
    },
    {
      "facilityId": 1000020541,
      "epaFacId": "100000175124",
      "facNm": null,
      "parntCo1Nm": null,
      "facDunsNu": null,
      "sbmsnTypeCd": "R",
      "facStreet1Tx": null,
      "facStreet2Tx": null,
      "facCityNm": null,
      "facStateCd": null,
      "countyNm": null,
      "facZipCd": null,
      "facZip4Cd": null,
      "receiptDa": "2011-02-21T00:00:00.000",
      "facLatDecMs": null,
      "facLongDecMs": null,
      "lepcNm": null,
      "oshaPsmCd": null,
      "epcra302Cd": null,
      "caaTitleVCd": null,
      "deregisteredDate": null,
      "emergencyPlan": null,
      "processes": null
    },
    {
      "facilityId": 45022,
      "epaFacId": "100000175124",
      "facNm": null,
      "parntCo1Nm": null,
      "facDunsNu": null,
      "sbmsnTypeCd": "R",
      "facStreet1Tx": null,
      "facStreet2Tx": null,
      "facCityNm": null,
      "facStateCd": null,
      "countyNm": null,
      "facZipCd": null,
      "facZip4Cd": null,
      "receiptDa": "2006-02-27T00:00:00.000",
      "facLatDecMs": null,
      "facLongDecMs": null,
      "lepcNm": null,
      "oshaPsmCd": null,
      "epcra302Cd": null,
      "caaTitleVCd": null,
      "deregisteredDate": null,
      "emergencyPlan": null,
      "processes": null
    },
    {
      "facilityId": 23237,
      "epaFacId": "100000175124",
      "facNm": null,
      "parntCo1Nm": null,
      "facDunsNu": null,
      "sbmsnTypeCd": "F",
      "facStreet1Tx": null,
      "facStreet2Tx": null,
      "facCityNm": null,
      "facStateCd": null,
      "countyNm": null,
      "facZipCd": null,
      "facZip4Cd": null,
      "receiptDa": "2001-04-13T00:00:00.000",
      "facLatDecMs": null,
      "facLongDecMs": null,
      "lepcNm": null,
      "oshaPsmCd": null,
      "epcra302Cd": null,
      "caaTitleVCd": null,
      "deregisteredDate": null,
      "emergencyPlan": null,
      "processes": null
    }
  ]
}