{
  "facilityId": 1000082872,
  "epaFacId": "100000219729",
  "facNm": "Ag Partners Cooperative, Inc - Powhattan NH3",
  "parntCo1Nm": null,
  "facDunsNu": null,
  "sbmsnTypeCd": "R",
  "facStreet1Tx": "928 180th St.",
  "facStreet2Tx": null,
  "facCityNm": "Powhattan",
  "facStateCd": "KS",
  "countyNm": "BROWN",
  "facZipCd": "66527",
  "facZip4Cd": null,
  "receiptDa": "2019-10-03T13:40:15.000",
  "facLatDecMs": "39.769209",
  "facLongDecMs": "-95.634151",
  "lepcNm": "Brown County LEPC",
  "oshaPsmCd": null,
  "epcra302Cd": "Y",
  "caaTitleVCd": null,
  "deregisteredDate": null,
  "emergencyPlan": {
    "communityPlanCd": "Y",
    "facilityPlanCd": null,
    "responseActionsCd": null,
    "publicProceduresCd": null,
    "healthcareCd": null,
    "agencyNm": "Brown Co. LEPC",
    "agencyPhoneNm": "7857427871",
    "_links": {
      "facility": {
        "href": "https://cdxapps.epa.gov/olem-rmp-pds/api/facilities/1000082872"
      }
    }
  },
  "processes": [
    {
      "programLevelCd": 2,
      "processNaics": [
        {
          "description": "Farm Supplies Merchant Wholesalers ",
          "naicsCd": "42491",
          "_links": {
            "naics": {
              "href": "https://cdxapps.epa.gov/olem-rmp-pds/api/naics-codes/42491"
            }
          }
        }
      ],
      "processChemicals": [
        {
          "flammableMixChems": [],
          "chemicalNm": "Ammonia (anhydrous)",
          "casNu": "7664-41-7",
          "flamToxCd": "T",
          "_links": {
            "chemical": {
              "href": "https://cdxapps.epa.gov/olem-rmp-pds/api/chemicals/56"
            }
          }
        }
      ],
      "_links": {
        "facility": {
          "href": "https://cdxapps.epa.gov/olem-rmp-pds/api/facilities/1000082872"
        }
      }
    }
  ],
  "_links": {
    "self": {
      "href": "https://cdxapps.epa.gov/olem-rmp-pds/api/facilities/1000082872"
    },
    "facility": {
      "href": "https://cdxapps.epa.gov/olem-rmp-pds/api/facilities/1000082872"
    }
  }
}