{
  "_embedded": [
    {
      "facilityId": 1000083951,
      "epaFacId": "100000189903",
      "facNm": null,
      "parntCo1Nm": null,
      "facDunsNu": null,
      "sbmsnTypeCd": "R",
      "facStreet1Tx": null,
      "facStreet2Tx": null,
      "facCityNm": null,
      "facStateCd": null,
      "countyNm": null,
      "facZipCd": null,
      "facZip4Cd": null,
      "receiptDa": "2019-11-25T00:00:00.000",
      "facLatDecMs": null,
      "facLongDecMs": null,
      "lepcNm": null,
      "oshaPsmCd": null,
      "epcra302Cd": null,
      "caaTitleVCd": null,
      "deregisteredDate": "2024-04-19T00:00:00.000",
      "emergencyPlan": null,
      "processes": null
    },
    {
      "facilityId": 1000047697,
      "epaFacId": "100000189903",
      "facNm": null,
      "parntCo1Nm": null,
      "facDunsNu": null,
      "sbmsnTypeCd": "R",
      "facStreet1Tx": null,
      "facStreet2Tx": null,
      "facCityNm": null,
      "facStateCd": null,
      "countyNm": null,
      "facZipCd": null,
      "facZip4Cd": null,
      "receiptDa": "2014-11-26T00:00:00.000",
      "facLatDecMs": null,
      "facLongDecMs": null,
      "lepcNm": null,
      "oshaPsmCd": null,
      "epcra302Cd": null,
      "caaTitleVCd": null,
      "deregisteredDate": "2024-04-19T00:00:00.000",
      "emergencyPlan": null,
      "processes": null
    },
    {
      "facilityId": 55763,
      "epaFacId": "100000189903",
      "facNm": null,
      "parntCo1Nm": null,
      "facDunsNu": null,
      "sbmsnTypeCd": "R",
      "facStreet1Tx": null,
      "facStreet2Tx": null,
      "facCityNm": null,
      "facStateCd": null,
      "countyNm": null,
      "facZipCd": null,
      "facZip4Cd": null,
      "receiptDa": "2009-07-14T00:00:00.000",
      "facLatDecMs": null,
      "facLongDecMs": null,
      "lepcNm": null,
      "oshaPsmCd": null,
      "epcra302Cd": null,
      "caaTitleVCd": null,
      "deregisteredDate": "2024-04-19T00:00:00.000",
      "emergencyPlan": null,
      "processes": null
    },
    {
      "facilityId": 41381,
      "epaFacId": "100000189903",
      "facNm": null,
      "parntCo1Nm": null,
      "facDunsNu": null,
      "sbmsnTypeCd": "F",
      "facStreet1Tx": null,
      "facStreet2Tx": null,
      "facCityNm": null,
      "facStateCd": null,
      "countyNm": null,
      "facZipCd": null,
      "facZip4Cd": null,
      "receiptDa": "2004-11-29T00:00:00.000",
      "facLatDecMs": null,
      "facLongDecMs": null,
      "lepcNm": null,
      "oshaPsmCd": null,
      "epcra302Cd": null,
      "caaTitleVCd": null,
      "deregisteredDate": "2024-04-19T00:00:00.000",
      "emergencyPlan": null,
      "processes": null
    }
  ]
}