{
  "_embedded": [
    {
      "facilityId": 1000049896,
      "epaFacId": "100000012719",
      "facNm": null,
      "parntCo1Nm": null,
      "facDunsNu": null,
      "sbmsnTypeCd": "R",
      "facStreet1Tx": null,
      "facStreet2Tx": null,
      "facCityNm": null,
      "facStateCd": null,
      "countyNm": null,
      "facZipCd": null,
      "facZip4Cd": null,
      "receiptDa": "2015-05-15T00:00:00.000",
      "facLatDecMs": null,
      "facLongDecMs": null,
      "lepcNm": null,
      "oshaPsmCd": null,
      "epcra302Cd": null,
      "caaTitleVCd": null,
      "deregisteredDate": "2016-03-11T00:00:00.000",
      "emergencyPlan": null,
      "processes": null
    },
    {
      "facilityId": 1000013488,
      "epaFacId": "100000012719",
      "facNm": null,
      "parntCo1Nm": null,
      "facDunsNu": null,
      "sbmsnTypeCd": "R",
      "facStreet1Tx": null,
      "facStreet2Tx": null,
      "facCityNm": null,
      "facStateCd": null,
      "countyNm": null,
      "facZipCd": null,
      "facZip4Cd": null,
      "receiptDa": "2010-06-09T00:00:00.000",
      "facLatDecMs": null,
      "facLongDecMs": null,
      "lepcNm": null,
      "oshaPsmCd": null,
      "epcra302Cd": null,
      "caaTitleVCd": null,
      "deregisteredDate": "2016-03-11T00:00:00.000",
      "emergencyPlan": null,
      "processes": null
    },
    {
      "facilityId": 1000011864,
      "epaFacId": "100000012719",
      "facNm": null,
      "parntCo1Nm": null,
      "facDunsNu": null,
      "sbmsnTypeCd": "R",
      "facStreet1Tx": null,
      "facStreet2Tx": null,
      "facCityNm": null,
      "facStateCd": null,
      "countyNm": null,
      "facZipCd": null,
      "facZip4Cd": null,
      "receiptDa": "2009-12-02T00:00:00.000",
      "facLatDecMs": null,
      "facLongDecMs": null,
      "lepcNm": null,
      "oshaPsmCd": null,
      "epcra302Cd": null,
      "caaTitleVCd": null,
      "deregisteredDate": "2016-03-11T00:00:00.000",
      "emergencyPlan": null,
      "processes": null
    },
    {
      "facilityId": 1000003838,
      "epaFacId": "100000012719",
      "facNm": null,
      "parntCo1Nm": null,
      "facDunsNu": null,
      "sbmsnTypeCd": "R",
      "facStreet1Tx": null,
      "facStreet2Tx": null,
      "facCityNm": null,
      "facStateCd": null,
      "countyNm": null,
      "facZipCd": null,
      "facZip4Cd": null,
      "receiptDa": "2009-06-17T00:00:00.000",
      "facLatDecMs": null,
      "facLongDecMs": null,
      "lepcNm": null,
      "oshaPsmCd": null,
      "epcra302Cd": null,
      "caaTitleVCd": null,
      "deregisteredDate": "2016-03-11T00:00:00.000",
      "emergencyPlan": null,
      "processes": null
    },
    {
      "facilityId": 28698,
      "epaFacId": "100000012719",
      "facNm": null,
      "parntCo1Nm": null,
      "facDunsNu": null,
      "sbmsnTypeCd": "R",
      "facStreet1Tx": null,
      "facStreet2Tx": null,
      "facCityNm": null,
      "facStateCd": null,
      "countyNm": null,
      "facZipCd": null,
      "facZip4Cd": null,
      "receiptDa": "2003-08-11T00:00:00.000",
      "facLatDecMs": null,
      "facLongDecMs": null,
      "lepcNm": null,
      "oshaPsmCd": null,
      "epcra302Cd": null,
      "caaTitleVCd": null,
      "deregisteredDate": "2016-03-11T00:00:00.000",
      "emergencyPlan": null,
      "processes": null
    },
    {
      "facilityId": 16758,
      "epaFacId": "100000012719",
      "facNm": null,
      "parntCo1Nm": null,
      "facDunsNu": null,
      "sbmsnTypeCd": "F",
      "facStreet1Tx": null,
      "facStreet2Tx": null,
      "facCityNm": null,
      "facStateCd": null,
      "countyNm": null,
      "facZipCd": null,
      "facZip4Cd": null,
      "receiptDa": "1999-05-24T00:00:00.000",
      "facLatDecMs": null,
      "facLongDecMs": null,
      "lepcNm": null,
      "oshaPsmCd": null,
      "epcra302Cd": null,
      "caaTitleVCd": null,
      "deregisteredDate": "2016-03-11T00:00:00.000",
      "emergencyPlan": null,
      "processes": null
    }
  ]
}