{
  "facilityId": 1000103706,
  "epaFacId": "100000249867",
  "facNm": "Norfolk LPG Terminal",
  "parntCo1Nm": "NGL Supply Terminal Company, LLC",
  "facDunsNu": null,
  "sbmsnTypeCd": "F",
  "facStreet1Tx": "100B Remington Avenue",
  "facStreet2Tx": "",
  "facCityNm": "Norfolk",
  "facStateCd": "NY",
  "countyNm": " ST. LAWRENCE",
  "facZipCd": "13667",
  "facZip4Cd": "",
  "receiptDa": "2022-12-26T00:00:00.000",
  "facLatDecMs": "44.808314",
  "facLongDecMs": "-74.995719",
  "lepcNm": "St. Lawrence County LEPC",
  "oshaPsmCd": "Y",
  "epcra302Cd": null,
  "caaTitleVCd": null,
  "deregisteredDate": null,
  "emergencyPlan": {
    "communityPlanCd": "Y",
    "facilityPlanCd": "Y",
    "responseActionsCd": "Y",
    "publicProceduresCd": "Y",
    "healthcareCd": "Y",
    "agencyNm": "Norfolk Volunteer Fire Department",
    "agencyPhoneNm": "3153846182",
    "_links": {
      "facility": {
        "href": "https://cdxapps.epa.gov/olem-rmp-pds/api/facilities/1000103706"
      }
    }
  },
  "processes": [
    {
      "programLevelCd": 3,
      "processNaics": [
        {
          "description": "Petroleum Bulk Stations and Terminals ",
          "naicsCd": "42471",
          "_links": {
            "naics": {
              "href": "https://cdxapps.epa.gov/olem-rmp-pds/api/naics-codes/42471"
            }
          }
        }
      ],
      "processChemicals": [
        {
          "flammableMixChems": [],
          "chemicalNm": "Propane",
          "casNu": "74-98-6",
          "flamToxCd": "F",
          "_links": {
            "chemical": {
              "href": "https://cdxapps.epa.gov/olem-rmp-pds/api/chemicals/98"
            }
          }
        }
      ],
      "_links": {
        "facility": {
          "href": "https://cdxapps.epa.gov/olem-rmp-pds/api/facilities/1000103706"
        }
      }
    }
  ],
  "_links": {
    "self": {
      "href": "https://cdxapps.epa.gov/olem-rmp-pds/api/facilities/1000103706"
    },
    "facility": {
      "href": "https://cdxapps.epa.gov/olem-rmp-pds/api/facilities/1000103706"
    }
  }
}