{
  "facilityId": 11462,
  "epaFacId": "100000121227",
  "facNm": "Continental Cement Company, LLC",
  "parntCo1Nm": null,
  "facDunsNu": 4782587,
  "sbmsnTypeCd": "F",
  "facStreet1Tx": "10107 Highway 79",
  "facStreet2Tx": null,
  "facCityNm": "Hannibal",
  "facStateCd": "MO",
  "countyNm": "RALLS",
  "facZipCd": "63401",
  "facZip4Cd": null,
  "receiptDa": "1999-06-22T00:00:00.000",
  "facLatDecMs": "39.681889",
  "facLongDecMs": "-91.330556",
  "lepcNm": "Marion/Ralls County LEPC",
  "oshaPsmCd": null,
  "epcra302Cd": "Y",
  "caaTitleVCd": "Y",
  "deregisteredDate": null,
  "emergencyPlan": {
    "communityPlanCd": "Y",
    "facilityPlanCd": "Y",
    "responseActionsCd": "Y",
    "publicProceduresCd": "Y",
    "healthcareCd": "Y",
    "agencyNm": "Hannibal Fire Department",
    "agencyPhoneNm": "5732210657",
    "_links": {
      "facility": {
        "href": "https://cdxapps.epa.gov/olem-rmp-pds/api/facilities/11462"
      }
    }
  },
  "processes": [
    {
      "programLevelCd": 2,
      "processNaics": [
        {
          "description": "Cement Manufacturing",
          "naicsCd": "32731",
          "_links": {
            "naics": {
              "href": "https://cdxapps.epa.gov/olem-rmp-pds/api/naics-codes/32731"
            }
          }
        }
      ],
      "processChemicals": [
        {
          "flammableMixChems": [],
          "chemicalNm": "Ethyl ether  [Ethane, 1,1'-oxybis-]",
          "casNu": "60-29-7",
          "flamToxCd": "F",
          "_links": {
            "chemical": {
              "href": "https://cdxapps.epa.gov/olem-rmp-pds/api/chemicals/92"
            }
          }
        }
      ],
      "_links": {
        "facility": {
          "href": "https://cdxapps.epa.gov/olem-rmp-pds/api/facilities/11462"
        }
      }
    }
  ],
  "_links": {
    "self": {
      "href": "https://cdxapps.epa.gov/olem-rmp-pds/api/facilities/11462"
    },
    "facility": {
      "href": "https://cdxapps.epa.gov/olem-rmp-pds/api/facilities/11462"
    }
  }
}